MVC/__init__.py
MVC/mvcconnection.py
examples/README.md
examples/SkyhighSSEListUpdate/SkyhighSSEListUpdate.py
examples/SkyhighSSEListUpdate/list_1234.csv
examples/SkyhighSSEPolicyBackup/SkyhighSSEPolicyBackup.py
mvc_python-0.0.10.dist-info/METADATA
mvc_python-0.0.10.dist-info/WHEEL
mvc_python-0.0.10.dist-info/licenses/LICENSE
mvc_python-0.0.10.dist-info/RECORD
