Metadata-Version: 2.1
Name: MVC-Python
Version: 0.0.10
Summary: A python module for Skyhigh SSE API and administrative access
Project-URL: Homepage, https://github.com/zengelan/MVC-Python
Project-URL: Bug Tracker, https://github.com/zengelan/MVC-Python/issues
Project-URL: Source, https://github.com/zengelan/MVC-Python
Author-email: Andreas Zengel <andreas.zengel@skyhighsecurity.com>, Andreas Zengel <andreas.zengel@gmail.com>
License-File: LICENSE
Classifier: License :: OSI Approved :: GNU General Public License v3 (GPLv3)
Classifier: Operating System :: OS Independent
Classifier: Programming Language :: Python :: 3
Requires-Python: >=3.8
Requires-Dist: requests>=2.26
